change_point_analyzer/__init__.py
change_point_analyzer/main.py
change_point_analyzer-0.0.5.dist-info/METADATA
change_point_analyzer-0.0.5.dist-info/WHEEL
change_point_analyzer-0.0.5.dist-info/RECORD
